libpy/__init__.py
libpy/app/__init__.py
libpy/app/segmentation/__init__.py
libpy/app/segmentation/predict.py
libpy/app/segmentation/components/__init__.py
libpy/app/segmentation/components/models/ERFNet.py
libpy/app/segmentation/components/models/HardNet.py
libpy/app/segmentation/components/models/__init__.py
libpy/app/segmentation/utils/__init__.py
libpy/app/segmentation/utils/segmentation.py
libpy/test/__init__.py
libpy/test/hello.py
libpy/torch/__init__.py
libpy/torch/models/ERFNet.py
libpy/torch/models/HardNet.py
libpy/torch/models/InceptionV1.py
libpy/torch/models/UNet.py
libpy/torch/models/__init__.py
libpy/torch/models/alexnet.py
libpy/torch/models/bcnn.py
libpy/torch/models/resnet18.py
libpy/torch/models/vgg16.py
libpycity945-0.0.2.dist-info/LICENSE
libpycity945-0.0.2.dist-info/METADATA
libpycity945-0.0.2.dist-info/WHEEL
libpycity945-0.0.2.dist-info/top_level.txt
libpycity945-0.0.2.dist-info/RECORD
