Metadata-Version: 2.1
Name: libpycity945
Version: 0.0.2
Summary: A small example package
Home-page: https://github.com/pypa/sampleproject
Author: city945
Author-email: 2654229893@qq.com
License: UNKNOWN
Platform: UNKNOWN
Classifier: Programming Language :: Python :: 3
Classifier: License :: OSI Approved :: MIT License
Classifier: Operating System :: OS Independent
Requires-Python: >=3.6
Requires-Dist: backcall (==0.2.0)
Requires-Dist: chardet (==3.0.4)
Requires-Dist: decorator (==4.4.2)
Requires-Dist: idna (==2.10)
Requires-Dist: imageio (==2.9.0)
Requires-Dist: ipdb (==0.13.4)
Requires-Dist: ipython (==7.19.0)
Requires-Dist: ipython-genutils (==0.2.0)
Requires-Dist: jedi (==0.17.2)
Requires-Dist: jsonpatch (==1.28)
Requires-Dist: jsonpointer (==2.0)
Requires-Dist: numpy (==1.19.4)
Requires-Dist: opencv-python (==4.4.0.46)
Requires-Dist: parso (==0.7.1)
Requires-Dist: pexpect (==4.8.0)
Requires-Dist: pickleshare (==0.7.5)
Requires-Dist: pillow (==8.0.1)
Requires-Dist: prompt-toolkit (==3.0.8)
Requires-Dist: ptyprocess (==0.6.0)
Requires-Dist: pygments (==2.7.2)
Requires-Dist: pyyaml (==5.3.1)
Requires-Dist: pyzmq (==20.0.0)
Requires-Dist: requests (==2.25.0)
Requires-Dist: scipy (==1.5.4)
Requires-Dist: six (==1.15.0)
Requires-Dist: torch (==1.4.0)
Requires-Dist: torchfile (==0.1.0)
Requires-Dist: torchnet (==0.0.4)
Requires-Dist: torchsummary (==1.5.1)
Requires-Dist: torchvision (==0.5.0)
Requires-Dist: tornado (==6.1)
Requires-Dist: tqdm (==4.54.0)
Requires-Dist: traitlets (==5.0.5)
Requires-Dist: urllib3 (==1.26.2)
Requires-Dist: visdom (==0.1.8.9)
Requires-Dist: wcwidth (==0.2.5)
Requires-Dist: websocket-client (==0.57.0)
